heta/__init__.py
heta/heta_hash.py
heta/module.py
heta/repo.py
heta/search.py
heta-1.0.2.dist-info/LICENSE
heta-1.0.2.dist-info/METADATA
heta-1.0.2.dist-info/WHEEL
heta-1.0.2.dist-info/top_level.txt
heta-1.0.2.dist-info/RECORD
