Metadata-Version: 2.1
Name: heta
Version: 1.0.2
Summary: Library for works with heta.
Home-page: https://github.com/FajoX1/heta
Author: Fajox
Author-email: pybytee@gmail.com
License: MIT
Classifier: Programming Language :: Python :: 3
Classifier: License :: OSI Approved :: MIT License
Classifier: Operating System :: OS Independent
License-File: LICENSE
Requires-Dist: requests
